mfetcher/Loader.py
mfetcher/__init__.py
mfetcher/command_line.py
mfetcher/download.py
mfetcher/download_chapter.py
mfetcher/fetcher.py
mfetcher/providers.py
mfetcher/test.py
mfetcher/utils.py
mfetcher-0.2.dist-info/LICENCE
mfetcher-0.2.dist-info/METADATA
mfetcher-0.2.dist-info/WHEEL
mfetcher-0.2.dist-info/entry_points.txt
mfetcher-0.2.dist-info/top_level.txt
mfetcher-0.2.dist-info/RECORD
