Metadata-Version: 2.1
Name: mfetcher
Version: 0.2
Summary: A simple cli tool to download mangas scan from the internet scan provider to your local file system
Home-page: https://github.com/sh1ftsh/mangas-scan-fetch
Author: Aurel Megnigbeto
Author-email: shiftsh@protonmail.ch
License: MIT
Platform: UNKNOWN
Classifier: Programming Language :: Python :: 3
Classifier: License :: OSI Approved :: MIT License
Classifier: Operating System :: OS Independent
Requires-Dist: docopt
Requires-Dist: requests
